clusterclienttest-0.2.0.dist-info/DESCRIPTION.rst
clusterclienttest-0.2.0.dist-info/RECORD
clusterclienttest-0.2.0.dist-info/WHEEL
clusterclienttest-0.2.0.dist-info/top_level.txt
clusterclienttest-0.2.0.dist-info/METADATA
clusterclienttest-0.2.0.dist-info/metadata.json
clusterclienttest/__main__.py
clusterclienttest/__init__.py
