Metadata-Version: 2.0
Name: clusterclienttest
Version: 0.2.0
Summary: Client for compute nodes to communicate via REST API with master server.
Home-page: https://github.com/RayCrafter/clusterclienttest
Author: David Zuber
Author-email: zuber.david@gmx.de
License: BSD
Keywords: clusterclienttest
Platform: UNKNOWN
Classifier: Development Status :: 4 - Beta
Classifier: Intended Audience :: Developers
Classifier: License :: OSI Approved :: BSD License
Classifier: Natural Language :: English
Classifier: Programming Language :: Python :: 2
Classifier: Programming Language :: Python :: 2.7
Classifier: Programming Language :: Python :: 3
Classifier: Programming Language :: Python :: 3.3
Classifier: Programming Language :: Python :: 3.4
Requires-Dist: requests-oauthlib
Requires-Dist: oauthlib
Requires-Dist: clusterlogger
